{
    "parent": "byte:gameplay/root",
    "criteria": {
        "dragon_breath": {
            "conditions": {
                "player": {
                    "equipment": {
                        "mainhand": {
                            "items": [
                                "dragon_breath"
                            ]
                        }
                    },
                    "flags": {
                        "is_sneaking": false
                    }
                }
            },
            "trigger": "location"
        }
    },
    "requirements": [
        [
            "dragon_breath"
        ]
    ],
    "rewards": {
        "function": "byte:gameplay/animation/dragon_breath"
    }
}